{
  "as_of_et": "2026-07-13 11:40 ET",
  "as_of_utc": "2026-07-13T15:40:50Z",
  "amzn_price": 248.82,
  "change_pct": 1.42,
  "legs": [
    {
      "leg": "AUG280",
      "symbol": "AMZN2621H280",
      "strike": 280,
      "expiry": "2026-08-21",
      "dte": 39,
      "premium_sold": 3.6,
      "bid": 4.15,
      "ask": 4.3,
      "mid": 4.22,
      "profit_pct": -17.2
    },
    {
      "leg": "SEP280",
      "symbol": "AMZN260918C280",
      "strike": 280,
      "expiry": "2026-09-18",
      "dte": 67,
      "premium_sold": 4.76,
      "bid": 6.65,
      "ask": 6.85,
      "mid": 6.75,
      "profit_pct": -41.8
    },
    {
      "leg": "OCT275",
      "symbol": "AMZN261016C275",
      "strike": 275,
      "expiry": "2026-10-16",
      "dte": 95,
      "premium_sold": 5.69,
      "bid": 10.6,
      "ask": 10.85,
      "mid": 10.72,
      "profit_pct": -88.4
    }
  ]
}